{
  "command_timeout": 5,
  "templates_folder": "_Bin/_Templates",
  "templates_pairs": [
    [
      "getWeather",
      "curl wttr.in/Portland+Maine\\format=\"%l:+%c+%t+feels+like+%f\\nSunrise:+%S\\nSunset:++%s\\nMoon:++++%m\\n\""
    ]
  ],
  "trigger_on_file_creation": true,
  "auto_jump_to_cursor": true,
  "enable_system_commands": true,
  "shell_path": "",
  "user_scripts_folder": "",
  "enable_folder_templates": true,
  "folder_templates": [
    {
      "folder": "Daily Notes",
      "template": "_Bin/_Templates/Daily Note.md"
    },
    {
      "folder": "Sessions",
      "template": "_Bin/_Templates/Session.md"
    },
    {
      "folder": "/",
      "template": "_Bin/_Templates/General Note.md"
    },
    {
      "folder": "Personal/Journal",
      "template": "_Bin/_Templates/Journal Entry.md"
    },
    {
      "folder": "Landing Zone",
      "template": "_Bin/_Templates/General Note.md"
    }
  ],
  "enable_file_templates": false,
  "file_templates": [
    {
      "regex": ".*",
      "template": ""
    }
  ],
  "syntax_highlighting": true,
  "syntax_highlighting_mobile": false,
  "enabled_templates_hotkeys": [
    "_Bin/_Templates/Single Task.md",
    "_Bin/_Templates/Single Session.md",
    "_Bin/_Templates/General Note.md",
    "_Bin/_Templates/Journal Entry.md",
    "_Bin/_Templates/Testing.md",
    "_Bin/_Templates/Doc to Table.md"
  ],
  "startup_templates": [
    ""
  ],
  "intellisense_render": 1,
  "enable_ribbon_icon": true
}